coix/__init__.py
coix/algo.py
coix/algo_test.py
coix/api.py
coix/api_test.py
coix/core.py
coix/core_test.py
coix/loss.py
coix/loss_test.py
coix/numpyro.py
coix/oryx.py
coix/oryx_test.py
coix/util.py
coix/util_test.py
coix-0.1.0.dist-info/LICENSE
coix-0.1.0.dist-info/WHEEL
coix-0.1.0.dist-info/METADATA
coix-0.1.0.dist-info/RECORD
