Metadata-Version: 2.1
Name: coix
Version: 0.1.0
Summary: Inference Combinators in JAX
Keywords: probabilistic machine learning,bayesian statistics
Author-email: coix authors <coix-dev@google.com>
Requires-Python: >=3.9
Classifier: License :: OSI Approved :: Apache Software License
Classifier: Intended Audience :: Science/Research
Requires-Dist: jax
Requires-Dist: jaxlib
Requires-Dist: numpy
Requires-Dist: numpyro
Requires-Dist: flax ; extra == "dev"
Requires-Dist: isort ; extra == "dev"
Requires-Dist: matplotlib ; extra == "dev"
Requires-Dist: numpyro ; extra == "dev"
Requires-Dist: optax ; extra == "dev"
Requires-Dist: pytest ; extra == "dev"
Requires-Dist: pytest-xdist ; extra == "dev"
Requires-Dist: pylint>=2.6.0 ; extra == "dev"
Requires-Dist: pyink ; extra == "dev"
Requires-Dist: ipython ; extra == "doc"
Requires-Dist: nbsphinx ; extra == "doc"
Requires-Dist: readthedocs-sphinx-search ; extra == "doc"
Requires-Dist: sphinx>=5 ; extra == "doc"
Requires-Dist: sphinx_rtd_theme ; extra == "doc"
Requires-Dist: sphinx-gallery ; extra == "doc"
Requires-Dist: oryx ; extra == "oryx"
Project-URL: changelog, https://github.com/jax-ml/coix/blob/main/CHANGELOG.md
Project-URL: documentation, https://coix.readthedocs.io
Project-URL: homepage, https://github.com/jax-ml/coix
Project-URL: repository, https://github.com/jax-ml/coix
Provides-Extra: dev
Provides-Extra: doc
Provides-Extra: oryx
